{
  "properties": {
    "parent": "arcade"
  },
  "data": [
    {
      "string": "Arcade (Classic Rule)",
      "fixedText": true,
      "type": "header"
    },
	{
      "label": "NOVICE",
      "description": "A slow game for beginners.",
      "fixedText": true,
      "default": true,
      "action": "submenu",
      "submenu": "mode/novice"
    },
	{
      "label": "SPECIAL",
      "description": "Your grade will depend on how well you play.",
      "fixedText": true,
      "action": "submenu",
      "submenu": "mode/special"
    },
    {
      "label": "SUDDEN",
      "description": "The pieces spawn on the ground and only get faster!",
      "fixedText": true,
      "action": "submenu",
      "submenu": "mode/sudden"
    },
    {
      "label": "NOVICE-TI",
      "description": "A slow game for beginners.",
      "fixedText": true,
      "action": "submenu",
      "submenu": "mode/noviceti"
    },
	{
      "label": "SPECIAL-TI",
      "description": "Your grade will depend on how well you play.",
      "fixedText": true,
      "action": "submenu",
      "submenu": "mode/specialti"
    },
    {
      "label": "SUDDEN-TI",
      "description": "The pieces spawn on the ground and only get faster!",
      "fixedText": true,
      "action": "submenu",
      "submenu": "mode/suddenti"
    },
	{
      "label": "PRESSURE",
      "description": "You have a time limit that cannot be reset nor extended. How many levels can you reach?",
	  "fixedText": true,
      "action": "submenu",
      "submenu": "mode/asuka"
    },
	{
      "label": "RALLY",
      "description": "Getting a perfect clear extends the time limit! How many perfect clears can you get?",
      "fixedText": true,
      "action": "submenu",
      "submenu": "mode/konoha"
    },
	{
      "label": "SUDDEN-AE",
      "description": "The ultimate test of block stacking skills. Only top-level players can reach far. (WIP)",
      "fixedText": true,
      "action": "submenu",
      "submenu": "mode/rounds"
    },
	{
      "label": "SPECIAL-AE 2.1",
      "description": "Congratulations! You have found a secret mode!",
      "fixedText": true,
	  "secretA": true,
      "action": "submenu",
      "submenu": "mode/normal21"
    },
	{
      "label": "SPECIAL-AE 3.1",
      "description": "Congratulations! You have found a secret mode!",
      "fixedText": true,
	  "secretA": true,
      "action": "submenu",
      "submenu": "mode/normal31"
    }
  ]
}
