{
  "properties": {
    "parent": "root",
    "vox": "menuretro"
  },
  "data": [
    {
      "string": "retroLabel",
      "langOverride": "menu_root",
      "type": "header"
    },
    {
      "string": "consoleLabel",
      "stringDesc": "consoleDescription",
      "default": true,
      "action": "submenu",
      "submenu": "mode/retro"
    },
    {
      "string": "handheldLabel",
      "stringDesc": "handheldDescription",
      "action": "submenu",
      "submenu": "mode/handheld"
    },
    {
      "string": "deluxeLabel",
      "stringDesc": "deluxeDescription",
      "action": "submenu",
      "submenu": "mode/deluxe"
    },
	{
      "string": "terminalLabel",
      "stringDesc": "terminalDescription",
	  "langOverride": "ue_additions",
      "action": "submenu",
      "submenu": "mode/terminal"
    },
    {
      "string": "segaLabel",
      "stringDesc": "segaDescription",
      "action": "submenu",
      "submenu": "mode/sega"
    },
	{
	  "secretA": true,
	  "string": "newCenturyLabel",
      "stringDesc": "newCenturyDescription",
	  "langOverride": "ue_additions",
      "action": "submenu",
      "submenu": "mode/newcentury"
    }
  ]
}
